yet_another_logger/__init__.py
yet_another_logger/enums.py
yet_another_logger/errors.py
yet_another_logger/schemas.py
yet_another_logger/utils.py
yet_another_logger/yet_another_logger.py
yet_another_logger-0.1.2.dist-info/METADATA
yet_another_logger-0.1.2.dist-info/WHEEL
yet_another_logger-0.1.2.dist-info/RECORD
