Metadata-Version: 2.1
Name: yet-another-logger
Version: 0.1.2
Summary: 
Author: ilteris.yucel
Author-email: ilteris.yucel@gmail.com
Requires-Python: >=3.12,<4.0
Classifier: Programming Language :: Python :: 3
Classifier: Programming Language :: Python :: 3.12
Requires-Dist: pydantic (>=2.8.2,<3.0.0)
Requires-Dist: toml (>=0.10.2,<0.11.0)
